{
    "text": {
      "DashBoard": "لوحة التحكم",
      "Employees": "الموظفين",
      "Articles": "المواد",
      "Matrices": "المصفوفات"
    },
    
        "login": {
          "email": "البريد الإلكتروني",
          "password": "كلمة المرور",
          "loginButton": "تسجيل",
          "invalidEmail": "بريد إلكتروني غير صالح",
          "requiredEmail": "البريد الإلكتروني مطلوب",
          "invalidPassword": "يجب أن تحتوي كلمة المرور على 6 أحرف على الأقل",
          "requiredPassword": "كلمة المرور مطلوبة",
          "loginError": "فشل تسجيل الدخول: "
        }
      
      
  }